cosmolog/__init__.py
cosmolog/_version.py
cosmolog/cosmologger.py
cosmolog/bin/__init__.py
cosmolog/bin/cli.py
cosmolog_dtkav-0.0.4.dist-info/AUTHORS
cosmolog_dtkav-0.0.4.dist-info/LICENSE
cosmolog_dtkav-0.0.4.dist-info/METADATA
cosmolog_dtkav-0.0.4.dist-info/WHEEL
cosmolog_dtkav-0.0.4.dist-info/entry_points.txt
cosmolog_dtkav-0.0.4.dist-info/top_level.txt
cosmolog_dtkav-0.0.4.dist-info/RECORD
