Metadata-Version: 2.1
Name: cosmolog-dtkav
Version: 0.0.4
Summary: cosmolog fork: do not use
Home-page: https://github.com/dtkav/cosmolog
Author: Isil Demir + Daniel Grossmann-Kavanagh
Author-email: me@danielgk.com
License: UNKNOWN
Platform: UNKNOWN
Requires-Dist: click (>=6.3)
Requires-Dist: pytz (>=2015.7)
Requires-Dist: python-dateutil (>=2.4.2)
Provides-Extra: test
Requires-Dist: pytest (>=3.0.2) ; extra == 'test'
Requires-Dist: flake8 (==3.2.0) ; extra == 'test'
Requires-Dist: freezegun (==0.3.9) ; extra == 'test'
